synthgenai/__init__.py
synthgenai/cli.py
synthgenai/dataset/__init__.py
synthgenai/dataset/base_dataset.py
synthgenai/dataset/dataset.py
synthgenai/dataset_genetors/__init__.py
synthgenai/dataset_genetors/classification_dataset_generator.py
synthgenai/dataset_genetors/dataset_generator.py
synthgenai/dataset_genetors/instruction_dataset_generator.py
synthgenai/dataset_genetors/preference_dataset_generator.py
synthgenai/dataset_genetors/raw_dataset_generator.py
synthgenai/dataset_genetors/sentiment_dataset_generator.py
synthgenai/dataset_genetors/summarization_dataset_generator.py
synthgenai/llm/__init__.py
synthgenai/llm/base_llm.py
synthgenai/llm/llm.py
synthgenai/prompts/description_system_prompt
synthgenai/prompts/description_user_prompt
synthgenai/prompts/entry_classification_system_prompt
synthgenai/prompts/entry_instruction_system_prompt
synthgenai/prompts/entry_preference_system_prompt
synthgenai/prompts/entry_raw_system_prompt
synthgenai/prompts/entry_sentiment_system_prompt
synthgenai/prompts/entry_summarization_system_prompt
synthgenai/prompts/entry_user_prompt
synthgenai/prompts/keyword_system_prompt
synthgenai/prompts/keyword_user_prompt
synthgenai/prompts/labels_system_prompt
synthgenai/prompts/labels_user_prompt
synthgenai/schemas/__init__.py
synthgenai/schemas/config.py
synthgenai/schemas/datasets.py
synthgenai/schemas/enums.py
synthgenai/schemas/messages.py
synthgenai/utils/__init__.py
synthgenai/utils/file_utils.py
synthgenai/utils/json_utils.py
synthgenai/utils/progress_utils.py
synthgenai/utils/prompt_utils.py
synthgenai/utils/text_utils.py
synthgenai/utils/yaml_utils.py
synthgenai-2.0.1.dist-info/METADATA
synthgenai-2.0.1.dist-info/WHEEL
synthgenai-2.0.1.dist-info/entry_points.txt
synthgenai-2.0.1.dist-info/licenses/LICENCE.txt
synthgenai-2.0.1.dist-info/RECORD
