Metadata-Version: 2.4
Name: synthgenai
Version: 2.0.1
Summary: SynthGenAI - Package for generating Synthetic Datasets.
Author-email: Bojan Jakimovski - Shekswess <jakimovski_bojan@outlook.com>
License: MIT License
License-File: LICENCE.txt
Requires-Python: >=3.10
Requires-Dist: boto3==1.40.28
Requires-Dist: datasets==4.0.0
Requires-Dist: huggingface-hub==0.34.4
Requires-Dist: jinja2==3.1.6
Requires-Dist: langfuse==3.3.4
Requires-Dist: litellm==1.77.0
Requires-Dist: loguru==0.7.3
Requires-Dist: pydantic==2.11.7
Requires-Dist: python-dotenv>=1.1.1
Requires-Dist: tqdm==4.67.1
Requires-Dist: typer==0.17.4
